{
    "image": "blue_filtered_s004_top_20250624_t1.jpg",
    "detections": [
        {
            "class": "vehicle",
            "bbox": [
                349,
                189,
                400,
                227
            ],
            "confidence": 0.8576232194900513
        },
        {
            "class": "vehicle",
            "bbox": [
                343,
                97,
                398,
                133
            ],
            "confidence": 0.8391221761703491
        },
        {
            "class": "vehicle",
            "bbox": [
                204,
                234,
                258,
                276
            ],
            "confidence": 0.8082249760627747
        },
        {
            "class": "vehicle",
            "bbox": [
                211,
                1,
                267,
                38
            ],
            "confidence": 0.804070770740509
        },
        {
            "class": "vehicle",
            "bbox": [
                534,
                520,
                566,
                636
            ],
            "confidence": 0.7935839891433716
        },
        {
            "class": "vehicle",
            "bbox": [
                469,
                500,
                495,
                606
            ],
            "confidence": 0.7928906083106995
        },
        {
            "class": "vehicle",
            "bbox": [
                528,
                379,
                560,
                489
            ],
            "confidence": 0.7882146835327148
        },
        {
            "class": "vehicle",
            "bbox": [
                358,
                146,
                398,
                177
            ],
            "confidence": 0.7850720882415771
        },
        {
            "class": "vehicle",
            "bbox": [
                561,
                168,
                588,
                264
            ],
            "confidence": 0.778709888458252
        },
        {
            "class": "vehicle",
            "bbox": [
                501,
                166,
                526,
                259
            ],
            "confidence": 0.7727742195129395
        },
        {
            "class": "vehicle",
            "bbox": [
                461,
                372,
                489,
                481
            ],
            "confidence": 0.7708898782730103
        },
        {
            "class": "vehicle",
            "bbox": [
                495,
                375,
                522,
                481
            ],
            "confidence": 0.7667338252067566
        },
        {
            "class": "vehicle",
            "bbox": [
                352,
                55,
                392,
                84
            ],
            "confidence": 0.763372540473938
        },
        {
            "class": "vehicle",
            "bbox": [
                588,
                382,
                623,
                487
            ],
            "confidence": 0.7599194645881653
        },
        {
            "class": "vehicle",
            "bbox": [
                346,
                11,
                392,
                43
            ],
            "confidence": 0.7440783977508545
        },
        {
            "class": "vehicle",
            "bbox": [
                618,
                179,
                639,
                261
            ],
            "confidence": 0.7242887616157532
        },
        {
            "class": "vehicle",
            "bbox": [
                349,
                0,
                397,
                7
            ],
            "confidence": 0.2768140733242035
        }
    ]
}