{
    "image": "blurred_0009_top_20250630_t0.jpg",
    "detections": [
        {
            "class": "vehicle",
            "bbox": [
                292,
                85,
                315,
                186
            ],
            "confidence": 0.7745760679244995
        },
        {
            "class": "vehicle",
            "bbox": [
                420,
                280,
                444,
                373
            ],
            "confidence": 0.7656787633895874
        },
        {
            "class": "vehicle",
            "bbox": [
                294,
                407,
                321,
                519
            ],
            "confidence": 0.7625682353973389
        },
        {
            "class": "vehicle",
            "bbox": [
                294,
                213,
                316,
                312
            ],
            "confidence": 0.7617560625076294
        }
    ]
}