{
    "image": "blurred_0010_top_20250711_t0.jpg",
    "detections": [
        {
            "class": "vehicle",
            "bbox": [
                85,
                212,
                152,
                392
            ],
            "confidence": 0.7315923571586609
        },
        {
            "class": "vehicle",
            "bbox": [
                294,
                203,
                349,
                375
            ],
            "confidence": 0.6949477195739746
        },
        {
            "class": "vehicle",
            "bbox": [
                436,
                206,
                499,
                374
            ],
            "confidence": 0.5676895976066589
        },
        {
            "class": "vehicle",
            "bbox": [
                240,
                208,
                300,
                391
            ],
            "confidence": 0.43686407804489136
        },
        {
            "class": "vehicle",
            "bbox": [
                544,
                210,
                607,
                379
            ],
            "confidence": 0.30085092782974243
        }
    ]
}