{
    "image": "blurred_0005_top_20250704_t1.JPG",
    "detections": [
        {
            "class": "vehicle",
            "bbox": [
                558,
                292,
                593,
                426
            ],
            "confidence": 0.7446460723876953
        },
        {
            "class": "vehicle",
            "bbox": [
                258,
                258,
                299,
                376
            ],
            "confidence": 0.7372655868530273
        },
        {
            "class": "vehicle",
            "bbox": [
                337,
                251,
                378,
                402
            ],
            "confidence": 0.733165979385376
        }
    ]
}