{
    "image": "bright_0005_top_20250705_t1.JPG",
    "detections": [
        {
            "class": "vehicle",
            "bbox": [
                391,
                317,
                412,
                370
            ],
            "confidence": 0.6243847012519836
        },
        {
            "class": "vehicle",
            "bbox": [
                407,
                78,
                428,
                104
            ],
            "confidence": 0.5587990283966064
        },
        {
            "class": "vehicle",
            "bbox": [
                370,
                87,
                387,
                134
            ],
            "confidence": 0.5347305536270142
        },
        {
            "class": "vehicle",
            "bbox": [
                457,
                49,
                474,
                82
            ],
            "confidence": 0.4228803515434265
        },
        {
            "class": "vehicle",
            "bbox": [
                479,
                45,
                495,
                77
            ],
            "confidence": 0.3991062045097351
        },
        {
            "class": "vehicle",
            "bbox": [
                496,
                37,
                513,
                74
            ],
            "confidence": 0.39301443099975586
        },
        {
            "class": "vehicle",
            "bbox": [
                458,
                53,
                473,
                79
            ],
            "confidence": 0.38715532422065735
        },
        {
            "class": "vehicle",
            "bbox": [
                507,
                34,
                523,
                73
            ],
            "confidence": 0.351531058549881
        },
        {
            "class": "vehicle",
            "bbox": [
                488,
                38,
                505,
                76
            ],
            "confidence": 0.3371715545654297
        },
        {
            "class": "vehicle",
            "bbox": [
                437,
                61,
                452,
                97
            ],
            "confidence": 0.3231518268585205
        },
        {
            "class": "vehicle",
            "bbox": [
                492,
                40,
                509,
                75
            ],
            "confidence": 0.277046263217926
        },
        {
            "class": "vehicle",
            "bbox": [
                455,
                55,
                472,
                80
            ],
            "confidence": 0.26050299406051636
        }
    ]
}