{
    "image": "bright_0009_top_20250619_t0.jpg",
    "detections": [
        {
            "class": "vehicle",
            "bbox": [
                149,
                407,
                304,
                541
            ],
            "confidence": 0.8890494108200073
        },
        {
            "class": "vehicle",
            "bbox": [
                360,
                310,
                509,
                439
            ],
            "confidence": 0.882251501083374
        },
        {
            "class": "vehicle",
            "bbox": [
                327,
                470,
                486,
                596
            ],
            "confidence": 0.8807790875434875
        },
        {
            "class": "vehicle",
            "bbox": [
                393,
                1,
                523,
                129
            ],
            "confidence": 0.8379933834075928
        },
        {
            "class": "vehicle",
            "bbox": [
                393,
                148,
                505,
                268
            ],
            "confidence": 0.8279759883880615
        }
    ]
}