{
    "image": "bright_0005_top_20250709_t1.png",
    "detections": [
        {
            "class": "vehicle",
            "bbox": [
                181,
                465,
                229,
                506
            ],
            "confidence": 0.787835955619812
        },
        {
            "class": "vehicle",
            "bbox": [
                580,
                391,
                624,
                448
            ],
            "confidence": 0.7629520297050476
        },
        {
            "class": "vehicle",
            "bbox": [
                255,
                498,
                295,
                547
            ],
            "confidence": 0.7599115967750549
        },
        {
            "class": "vehicle",
            "bbox": [
                286,
                175,
                311,
                246
            ],
            "confidence": 0.7215474247932434
        }
    ]
}