{
    "image": "bright_0005_top_20250702_t0.jpg",
    "detections": [
        {
            "class": "vehicle",
            "bbox": [
                163,
                432,
                363,
                565
            ],
            "confidence": 0.9143380522727966
        },
        {
            "class": "vehicle",
            "bbox": [
                164,
                56,
                353,
                211
            ],
            "confidence": 0.7148755192756653
        },
        {
            "class": "vehicle",
            "bbox": [
                165,
                536,
                356,
                640
            ],
            "confidence": 0.3798145651817322
        },
        {
            "class": "vehicle",
            "bbox": [
                160,
                563,
                373,
                640
            ],
            "confidence": 0.3146345913410187
        }
    ]
}