{
    "image": "bright_0006_top_20250707_t1.JPG",
    "detections": [
        {
            "class": "vehicle",
            "bbox": [
                0,
                361,
                109,
                547
            ],
            "confidence": 0.7855582237243652
        },
        {
            "class": "vehicle",
            "bbox": [
                161,
                170,
                197,
                280
            ],
            "confidence": 0.7612584233283997
        },
        {
            "class": "vehicle",
            "bbox": [
                97,
                172,
                131,
                275
            ],
            "confidence": 0.7354666590690613
        },
        {
            "class": "vehicle",
            "bbox": [
                254,
                156,
                289,
                267
            ],
            "confidence": 0.7187783122062683
        },
        {
            "class": "vehicle",
            "bbox": [
                218,
                157,
                253,
                267
            ],
            "confidence": 0.7140998244285583
        },
        {
            "class": "vehicle",
            "bbox": [
                293,
                164,
                328,
                271
            ],
            "confidence": 0.7002758979797363
        },
        {
            "class": "vehicle",
            "bbox": [
                129,
                174,
                162,
                276
            ],
            "confidence": 0.6962945461273193
        },
        {
            "class": "vehicle",
            "bbox": [
                0,
                159,
                33,
                277
            ],
            "confidence": 0.6941279172897339
        },
        {
            "class": "vehicle",
            "bbox": [
                60,
                162,
                93,
                276
            ],
            "confidence": 0.6446463465690613
        },
        {
            "class": "vehicle",
            "bbox": [
                31,
                159,
                64,
                277
            ],
            "confidence": 0.5890219807624817
        },
        {
            "class": "vehicle",
            "bbox": [
                37,
                157,
                72,
                277
            ],
            "confidence": 0.41253983974456787
        }
    ]
}