{
    "image": "bright_s012_top_20250619_t1.jpg",
    "detections": [
        {
            "class": "vehicle",
            "bbox": [
                191,
                303,
                291,
                370
            ],
            "confidence": 0.7859027981758118
        },
        {
            "class": "vehicle",
            "bbox": [
                473,
                248,
                516,
                419
            ],
            "confidence": 0.7656925916671753
        },
        {
            "class": "vehicle",
            "bbox": [
                406,
                259,
                450,
                419
            ],
            "confidence": 0.7405545711517334
        },
        {
            "class": "vehicle",
            "bbox": [
                100,
                134,
                146,
                308
            ],
            "confidence": 0.729617714881897
        }
    ]
}