{
    "image": "bright_s013_top_20250709_t0.JPG",
    "detections": [
        {
            "class": "vehicle",
            "bbox": [
                521,
                420,
                640,
                635
            ],
            "confidence": 0.7607293725013733
        },
        {
            "class": "vehicle",
            "bbox": [
                328,
                258,
                450,
                515
            ],
            "confidence": 0.7512362599372864
        },
        {
            "class": "vehicle",
            "bbox": [
                0,
                300,
                82,
                501
            ],
            "confidence": 0.7414432168006897
        }
    ]
}