{
    "image": "bright_s002_top_20250626_t1.jpg",
    "detections": [
        {
            "class": "vehicle",
            "bbox": [
                85,
                356,
                164,
                407
            ],
            "confidence": 0.8481215238571167
        },
        {
            "class": "vehicle",
            "bbox": [
                346,
                65,
                375,
                210
            ],
            "confidence": 0.8168942928314209
        },
        {
            "class": "vehicle",
            "bbox": [
                84,
                454,
                167,
                498
            ],
            "confidence": 0.8136594891548157
        },
        {
            "class": "vehicle",
            "bbox": [
                80,
                530,
                152,
                579
            ],
            "confidence": 0.7975785136222839
        },
        {
            "class": "vehicle",
            "bbox": [
                258,
                51,
                285,
                192
            ],
            "confidence": 0.7944716215133667
        }
    ]
}