{
    "image": "noisy_0001_top_20250623_t0.jpg",
    "detections": [
        {
            "class": "vehicle",
            "bbox": [
                134,
                130,
                214,
                182
            ],
            "confidence": 0.8627917170524597
        },
        {
            "class": "vehicle",
            "bbox": [
                595,
                217,
                638,
                319
            ],
            "confidence": 0.8088544011116028
        },
        {
            "class": "vehicle",
            "bbox": [
                237,
                143,
                266,
                277
            ],
            "confidence": 0.8000434041023254
        },
        {
            "class": "vehicle",
            "bbox": [
                280,
                147,
                306,
                275
            ],
            "confidence": 0.7946060299873352
        },
        {
            "class": "vehicle",
            "bbox": [
                320,
                151,
                348,
                279
            ],
            "confidence": 0.7891847491264343
        },
        {
            "class": "vehicle",
            "bbox": [
                543,
                236,
                589,
                352
            ],
            "confidence": 0.7736252546310425
        },
        {
            "class": "vehicle",
            "bbox": [
                261,
                440,
                392,
                534
            ],
            "confidence": 0.7291483283042908
        },
        {
            "class": "vehicle",
            "bbox": [
                0,
                115,
                14,
                185
            ],
            "confidence": 0.35196083784103394
        }
    ]
}