{
    "image": "noisy_s010_top_20250709_t0.JPG",
    "detections": [
        {
            "class": "vehicle",
            "bbox": [
                213,
                111,
                269,
                202
            ],
            "confidence": 0.8042831420898438
        },
        {
            "class": "vehicle",
            "bbox": [
                372,
                199,
                436,
                344
            ],
            "confidence": 0.803886890411377
        },
        {
            "class": "vehicle",
            "bbox": [
                1,
                503,
                65,
                622
            ],
            "confidence": 0.6285330057144165
        },
        {
            "class": "vehicle",
            "bbox": [
                149,
                251,
                212,
                355
            ],
            "confidence": 0.41384097933769226
        }
    ]
}