<PAMDataset>
  <Metadata>
    <MDI key="EXIF_ComponentsConfiguration">0x01 0x02 0x03 0x00</MDI>
    <MDI key="EXIF_DateTimeOriginal">2025:09:11 12:31:08</MDI>
    <MDI key="EXIF_ExifVersion">0221</MDI>
    <MDI key="EXIF_FlashpixVersion">0100</MDI>
    <MDI key="EXIF_Orientation">1</MDI>
    <MDI key="EXIF_PixelXDimension">1640</MDI>
    <MDI key="EXIF_PixelYDimension">916</MDI>
    <MDI key="EXIF_ResolutionUnit">2</MDI>
    <MDI key="EXIF_SceneCaptureType">0</MDI>
    <MDI key="EXIF_UserComment">Screenshot</MDI>
    <MDI key="EXIF_XResolution">(72)</MDI>
    <MDI key="EXIF_YResolution">(72)</MDI>
  </Metadata>
  <Metadata domain="IMAGE_STRUCTURE">
    <MDI key="SOURCE_COLOR_SPACE">YCbCr</MDI>
    <MDI key="INTERLEAVE">PIXEL</MDI>
    <MDI key="COMPRESSION">JPEG</MDI>
  </Metadata>
  <Metadata domain="xml:XMP" format="xml">
    <?xpacket begin="&#xFEFF;" id="W5M0MpCehiHzreSzNTczkc9d"?>
    <x:xmpmeta xmlns:x="adobe:ns:meta/" x:xmptk="XMP Core 6.0.0">
      <rdf:RDF xmlns:rdf="http://www.w3.org/1999/02/22-rdf-syntax-ns#">
        <rdf:Description rdf:about="" xmlns:photoshop="http://ns.adobe.com/photoshop/1.0/" xmlns:xmpNote="http://ns.adobe.com/xmp/note/" photoshop:DateCreated="2025-09-11T12:31:08" xmpNote:HasExtendedXMP="6990291632B3EBCAD0D34DE015EC3E4C" />
      </rdf:RDF>
    </x:xmpmeta>
    <?xpacket end="w"?>
  </Metadata>
  <PAMRasterBand band="1">
    <Metadata>
      <MDI key="STATISTICS_APPROXIMATE">YES</MDI>
      <MDI key="STATISTICS_MINIMUM">6</MDI>
      <MDI key="STATISTICS_MAXIMUM">253</MDI>
      <MDI key="STATISTICS_MEAN">72.300530222694</MDI>
      <MDI key="STATISTICS_STDDEV">46.543031887945</MDI>
      <MDI key="STATISTICS_VALID_PERCENT">100</MDI>
    </Metadata>
    <Metadata domain="IMAGE_STRUCTURE">
      <MDI key="COMPRESSION">JPEG</MDI>
    </Metadata>
  </PAMRasterBand>
  <PAMRasterBand band="2">
    <Metadata>
      <MDI key="STATISTICS_APPROXIMATE">YES</MDI>
      <MDI key="STATISTICS_MINIMUM">10</MDI>
      <MDI key="STATISTICS_MAXIMUM">253</MDI>
      <MDI key="STATISTICS_MEAN">95.609501590668</MDI>
      <MDI key="STATISTICS_STDDEV">41.472500731579</MDI>
      <MDI key="STATISTICS_VALID_PERCENT">100</MDI>
    </Metadata>
    <Metadata domain="IMAGE_STRUCTURE">
      <MDI key="COMPRESSION">JPEG</MDI>
    </Metadata>
  </PAMRasterBand>
  <PAMRasterBand band="3">
    <Metadata>
      <MDI key="STATISTICS_APPROXIMATE">YES</MDI>
      <MDI key="STATISTICS_MINIMUM">7</MDI>
      <MDI key="STATISTICS_MAXIMUM">252</MDI>
      <MDI key="STATISTICS_MEAN">72.871304347826</MDI>
      <MDI key="STATISTICS_STDDEV">46.404903175221</MDI>
      <MDI key="STATISTICS_VALID_PERCENT">100</MDI>
    </Metadata>
    <Metadata domain="IMAGE_STRUCTURE">
      <MDI key="COMPRESSION">JPEG</MDI>
    </Metadata>
  </PAMRasterBand>
</PAMDataset>
